LICENSE
MANIFEST.in
README.rst
setup.py
google/__init__.py
google/cloud/__init__.py
google/cloud/grpc/__init__.py
google/cloud/grpc/devtools/__init__.py
google/cloud/grpc/devtools/clouderrorreporting/__init__.py
google/cloud/grpc/devtools/clouderrorreporting/v1beta1/__init__.py
google/cloud/grpc/devtools/clouderrorreporting/v1beta1/common_pb2.py
google/cloud/grpc/devtools/clouderrorreporting/v1beta1/common_pb2_grpc.py
google/cloud/grpc/devtools/clouderrorreporting/v1beta1/error_group_service_pb2.py
google/cloud/grpc/devtools/clouderrorreporting/v1beta1/error_group_service_pb2_grpc.py
google/cloud/grpc/devtools/clouderrorreporting/v1beta1/error_stats_service_pb2.py
google/cloud/grpc/devtools/clouderrorreporting/v1beta1/error_stats_service_pb2_grpc.py
google/cloud/grpc/devtools/clouderrorreporting/v1beta1/report_errors_service_pb2.py
google/cloud/grpc/devtools/clouderrorreporting/v1beta1/report_errors_service_pb2_grpc.py
grpc_google_cloud_error_reporting_v1beta1.egg-info/PKG-INFO
grpc_google_cloud_error_reporting_v1beta1.egg-info/SOURCES.txt
grpc_google_cloud_error_reporting_v1beta1.egg-info/dependency_links.txt
grpc_google_cloud_error_reporting_v1beta1.egg-info/namespace_packages.txt
grpc_google_cloud_error_reporting_v1beta1.egg-info/requires.txt
grpc_google_cloud_error_reporting_v1beta1.egg-info/top_level.txt